app/__init__.py
app/db.py
app/main.py
app/prompt_builder.py
app/models/chunk.py
app/models/validation.py
app/prompts/__init__.py
app/services/__init__.py
app/services/chunking.py
app/services/embedding.py
app/services/generation.py
app/services/validator.py
app/utils/__init__.py
app/utils/cosine.py
app/utils/load.py
app/utils/search.py
app/utils/store.py
repoguard/__init__.py
repoguard/__main__.py
repoguard/cli.py
repoguard/docs.py
repoguard/format.py
repoguard/gitdiff.py
repoguard/repo.py
repoguard/run.py
repoguard_ai-1.0.5.dist-info/METADATA
repoguard_ai-1.0.5.dist-info/WHEEL
repoguard_ai-1.0.5.dist-info/entry_points.txt
repoguard_ai-1.0.5.dist-info/top_level.txt
repoguard_ai-1.0.5.dist-info/RECORD
