Metadata-Version: 2.4
Name: repoguard-ai
Version: 1.0.5
Summary: Repo-aware PR guideline validator
Requires-Python: >=3.9
Requires-Dist: requests>=2.28
Requires-Dist: pydantic>=2
Requires-Dist: fastapi==0.128.0
Requires-Dist: psycopg2-binary
